pvdeg/__init__.py
pvdeg/cli.py
pvdeg/collection.py
pvdeg/config.py
pvdeg/decorators.py
pvdeg/degradation.py
pvdeg/design.py
pvdeg/diffusion.py
pvdeg/fatigue.py
pvdeg/geospatial.py
pvdeg/geospatialscenario.py
pvdeg/humidity.py
pvdeg/letid.py
pvdeg/montecarlo.py
pvdeg/pysam.py
pvdeg/scenario.py
pvdeg/spectral.py
pvdeg/standards.py
pvdeg/symbolic.py
pvdeg/temperature.py
pvdeg/utilities.py
pvdeg/weather.py
pvdeg/data/AApermeation.json
pvdeg/data/DegradationDatabase.json
pvdeg/data/H2Opermeation.json
pvdeg/data/O2permeation.json
pvdeg/data/OPAL2.pvl
pvdeg/data/PVL_GenProfile.xlsx
pvdeg/data/albedo.json
pvdeg/data/module test data.csv
pvdeg/data/module_temperature.csv
pvdeg/data/psm3.csv
pvdeg/data/psm3_demo.csv
pvdeg/data/spectra.csv
pvdeg/data/wyller data.csv
pvdeg/data/xeff_demo.csv
pvdeg/data/xeff_demo.xlsx
pvdeg-0.7.0.dist-info/licenses/LICENSE.md
pvdeg-0.7.0.dist-info/METADATA
pvdeg-0.7.0.dist-info/WHEEL
pvdeg-0.7.0.dist-info/entry_points.txt
pvdeg-0.7.0.dist-info/top_level.txt
pvdeg-0.7.0.dist-info/RECORD
