Metadata-Version: 2.4
Name: pvdeg
Version: 0.7.0
Summary: Pvdeg is a python library that supports the calculation of degradation related parameters for photovoltaic (PV) modules.
Author-email: Pvdeg Python Developers <Michael.Kempe@nrel.gov>
Maintainer-email: Silvana.Ovaitt@nrel.gov
License: BSD-3
Project-URL: Homepage, https://github.com/NREL/PVDegradationTools
Project-URL: Bug Tracker, https://github.com/NREL/PVDegradationTools/issues
Project-URL: Documentation, https://pvdegradationtools.readthedocs.io/
Project-URL: Source Code, https://github.com/NREL/PVDegradationTools
Keywords: photovoltaic,solar,degradation,analysis,performance,module,PV
Classifier: Development Status :: 4 - Beta
Classifier: Operating System :: OS Independent
Classifier: Intended Audience :: Science/Research
Classifier: Programming Language :: Python :: 3
Classifier: Topic :: Scientific/Engineering
Requires-Python: >=3.10.0
License-File: LICENSE.md
Requires-Dist: aiohttp==3.12.14
Requires-Dist: numpy>=1.19.3
Requires-Dist: pvlib>=0.12.0
Requires-Dist: scipy>1.6.0
Requires-Dist: NREL-rex
Requires-Dist: cartopy
Requires-Dist: dask[dataframe]
Requires-Dist: dask-jobqueue
Requires-Dist: bokeh
Requires-Dist: geopy
Requires-Dist: h5netcdf
Requires-Dist: h5py<=3.14.0
Requires-Dist: jupyterlab
Requires-Dist: matplotlib
Requires-Dist: netCDF4
Requires-Dist: notebook
Requires-Dist: numba
Requires-Dist: openpyxl
Requires-Dist: pandas
Requires-Dist: photovoltaic
Requires-Dist: python-dateutil
Requires-Dist: pytz
Requires-Dist: seaborn
Requires-Dist: tables
Requires-Dist: tqdm
Requires-Dist: xarray
Requires-Dist: pre-commit
Requires-Dist: sympy
Requires-Dist: zarr
Requires-Dist: jupytext
Provides-Extra: docs
Requires-Dist: readthedocs-sphinx-search<0.4,>=0.3.1; extra == "docs"
Requires-Dist: sphinx<8,>=7.2.6; extra == "docs"
Requires-Dist: sphinx_rtd_theme<3,>=2.0.0; extra == "docs"
Requires-Dist: sphinx-gallery; extra == "docs"
Requires-Dist: nbsphinx; extra == "docs"
Requires-Dist: sphinx_toggleprompt; extra == "docs"
Requires-Dist: pydata_sphinx_theme; extra == "docs"
Requires-Dist: mistune==3.0.0; extra == "docs"
Provides-Extra: test
Requires-Dist: pytest; extra == "test"
Requires-Dist: pytest-cov; extra == "test"
Requires-Dist: nbval; extra == "test"
Requires-Dist: scikit-learn; extra == "test"
Requires-Dist: NREL-PySAM; extra == "test"
Provides-Extra: books
Requires-Dist: jupyter-book<2.0; extra == "books"
Provides-Extra: sam
Requires-Dist: NREL-PySAM; extra == "sam"
Provides-Extra: all
Requires-Dist: pvdeg[books,docs,sam,test]; extra == "all"
Dynamic: license-file
